quantamatics/__init__.py
quantamatics/core/APIClient.py
quantamatics/core/APIGateway.py
quantamatics/core/__init__.py
quantamatics/core/settings.py
quantamatics/core/utils.py
quantamatics/data/__init__.py
quantamatics/data/fundamentals.py
quantamatics/data/securityMaster.py
quantamatics/providers/Facteus.py
quantamatics/providers/TenTenData.py
quantamatics/providers/__init__.py
quantamatics/providers/config.py
quantamatics/providers/panelFactory.py
quantamatics/providers/panels.py
quantamatics-2.0.1.dist-info/LICENSE.txt
quantamatics-2.0.1.dist-info/METADATA
quantamatics-2.0.1.dist-info/WHEEL
quantamatics-2.0.1.dist-info/top_level.txt
quantamatics-2.0.1.dist-info/RECORD
