Metadata-Version: 2.1
Name: quantamatics
Version: 2.0.1
Summary: Quantamatics Open Source API Package
Home-page: https://github.com/Quantamatics/quantamatics
Maintainer: Facteus, Inc.
Classifier: Development Status :: 4 - Beta
Classifier: Programming Language :: Python
Classifier: Programming Language :: Python :: 3
Classifier: Programming Language :: Python :: 3.4
Classifier: Programming Language :: Python :: 3.5
Classifier: Programming Language :: Python :: 3.6
Classifier: Programming Language :: Python :: 3.7
Classifier: Programming Language :: Python :: 3.8
Classifier: Programming Language :: Python :: 3.9
Classifier: Programming Language :: Python :: 3.10
Classifier: Programming Language :: Python :: 3.11
Classifier: Intended Audience :: Science/Research
Classifier: Intended Audience :: Financial and Insurance Industry
Classifier: Intended Audience :: Customer Service
Classifier: Topic :: Scientific/Engineering :: Mathematics
Classifier: Operating System :: OS Independent
License-File: LICENSE.txt
Requires-Dist: setuptools
Requires-Dist: requests
Requires-Dist: python-jose[cryptography]
Requires-Dist: pyOpenSSL (>=21.0.0)
Requires-Dist: pandas
Requires-Dist: numpy
Requires-Dist: aiohttp[speedups]
Requires-Dist: nest-asyncio
